aestoolbox/__init__.py
aestoolbox/release.py
aestoolbox/core/__init__.py
aestoolbox/core/aes_schedule.py
aestoolbox/core/const.py
aestoolbox/core/base/__init__.py
aestoolbox/core/base/logs/__init__.py
aestoolbox/core/base/logs/logger.py
aestoolbox-0.0.4.data/scripts/aes-schedule
tests/__init__.py
tests/gfp.py
tests/test_aes_schedule.py
tests/test_vectors.py
aestoolbox-0.0.4.dist-info/LICENSE
aestoolbox-0.0.4.dist-info/METADATA
aestoolbox-0.0.4.dist-info/WHEEL
aestoolbox-0.0.4.dist-info/top_level.txt
aestoolbox-0.0.4.dist-info/RECORD
