Metadata-Version: 2.1
Name: aestoolbox
Version: 0.0.4
Summary: An AES Toolbox for computing Rijndael key schedule given a 128, 192, or 256-bit key.
Home-page: https://github.com/emdneto/aestoolbox.git
Author: Emídio Neto
License: MIT License
Keywords: AES Key Schedule Rijndael AES-128 AES-192 AES-192 AES Key     Expansion aeskeyschedule aes toolbox aes-key
Platform: UNKNOWN
Classifier: Intended Audience :: Developers
Classifier: License :: OSI Approved :: MIT License
Classifier: Natural Language :: English
Classifier: Programming Language :: Python :: 3
Classifier: Programming Language :: Python :: 3.8
Requires-Python: >=3.8
